odoo/addons/product_brand_tag_secondary/README.rst
odoo/addons/product_brand_tag_secondary/__init__.py
odoo/addons/product_brand_tag_secondary/__manifest__.py
odoo/addons/product_brand_tag_secondary/i18n/es.po
odoo/addons/product_brand_tag_secondary/i18n/it.po
odoo/addons/product_brand_tag_secondary/i18n/product_brand_tag_secondary.pot
odoo/addons/product_brand_tag_secondary/models/__init__.py
odoo/addons/product_brand_tag_secondary/models/product_brand.py
odoo/addons/product_brand_tag_secondary/models/product_brand_tag.py
odoo/addons/product_brand_tag_secondary/readme/CONTRIBUTORS.rst
odoo/addons/product_brand_tag_secondary/readme/DESCRIPTION.rst
odoo/addons/product_brand_tag_secondary/static/description/icon.png
odoo/addons/product_brand_tag_secondary/static/description/index.html
odoo/addons/product_brand_tag_secondary/tests/__init__.py
odoo/addons/product_brand_tag_secondary/tests/test_product_brand.py
odoo/addons/product_brand_tag_secondary/views/product_brand_tag_view.xml
odoo/addons/product_brand_tag_secondary/views/product_brand_view.xml
odoo14_addon_product_brand_tag_secondary-14.0.1.0.1.dev11.dist-info/METADATA
odoo14_addon_product_brand_tag_secondary-14.0.1.0.1.dev11.dist-info/WHEEL
odoo14_addon_product_brand_tag_secondary-14.0.1.0.1.dev11.dist-info/top_level.txt
odoo14_addon_product_brand_tag_secondary-14.0.1.0.1.dev11.dist-info/RECORD
